LICENSE
README.md
pyproject.toml
setup.cfg
setup.py
src/jgmd_util/__init__.py
src/jgmd_util/basic_util.py
src/jgmd_util/file_util.py
src/jgmd_util/input_util.py
src/jgmd_util/logging_util.py
src/jgmd_util.egg-info/PKG-INFO
src/jgmd_util.egg-info/SOURCES.txt
src/jgmd_util.egg-info/dependency_links.txt
src/jgmd_util.egg-info/requires.txt
src/jgmd_util.egg-info/top_level.txt